rtl/fifo.sv
module fifo #(
  parameter WIDTH = 8,
  parameter DEPTH = 16
)(
  input              clk,
  input              rst_n,   // active-low synchronous reset
  input              push,
  input  [WIDTH-1:0] din,
  input              pop,
  output reg [WIDTH-1:0] dout,
  output             full,
  output             empty,
  output reg [31:0]  count   // fixed width so Verilog compilers don't fight
);

  // Verilog-friendly clog2
  function integer clog2;
    input integer value;
    integer i;
    begin
      value = value - 1;
      for (i = 0; value > 0; i = i + 1)
        value = value >> 1;
      clog2 = i;
    end
  endfunction

  localparam ADDR_W = clog2(DEPTH);

  reg [WIDTH-1:0] mem [0:DEPTH-1];
  reg [ADDR_W:0]  wr_ptr, rd_ptr; // extra bit for full/empty

  wire wr_en = push && !full;
  wire rd_en = pop  && !empty;

  assign empty = (wr_ptr == rd_ptr);

  assign full  = (wr_ptr[ADDR_W] != rd_ptr[ADDR_W]) &&
                 (wr_ptr[ADDR_W-1:0] == rd_ptr[ADDR_W-1:0]);

  // write
  always @(posedge clk) begin
    if (wr_en) begin
      mem[wr_ptr[ADDR_W-1:0]] <= din;
    end
  end

  // read (registered output)
  always @(posedge clk) begin
    if (!rst_n) begin
      dout <= {WIDTH{1'b0}};
    end else if (rd_en) begin
      dout <= mem[rd_ptr[ADDR_W-1:0]];
    end
  end

  // pointers + count
  always @(posedge clk) begin
    if (!rst_n) begin
      wr_ptr <= { (ADDR_W+1){1'b0} };
      rd_ptr <= { (ADDR_W+1){1'b0} };
      count  <= 32'd0;
    end else begin
      case ({wr_en, rd_en})
        2'b10: count <= count + 1;
        2'b01: count <= count - 1;
        default: count <= count;
      endcase

      if (wr_en) wr_ptr <= wr_ptr + 1;
      if (rd_en) rd_ptr <= rd_ptr + 1;
    end
  end

endmodule

tb/tb_fifo.sv
module tb_fifo;

  localparam WIDTH = 8;
  localparam DEPTH = 16;

  reg clk, rst_n;
  reg push, pop;
  reg [WIDTH-1:0] din;

  wire [WIDTH-1:0] dout;
  wire full, empty;
  wire [31:0] count;

  fifo #(.WIDTH(WIDTH), .DEPTH(DEPTH)) dut (
    .clk(clk), .rst_n(rst_n), .push(push), .din(din),
    .pop(pop), .dout(dout), .full(full), .empty(empty), .count(count)
  );

  // Reference model: circular buffer
  reg [WIDTH-1:0] ref_mem [0:DEPTH-1];
  integer ref_wr, ref_rd;
  integer ref_count;

  // Temps
  integer i;
  integer wr_ok, rd_ok;
  reg [WIDTH-1:0] exp;

  // clock
  initial clk = 0;
  always #5 clk = ~clk;

  // waves
  initial begin
    $dumpfile("wave.vcd");
    $dumpvars(0, tb_fifo);
  end

  task do_reset;
    begin
      push = 0; pop = 0; din = 0;
      rst_n = 0;

      // reset reference model too
      ref_wr = 0; ref_rd = 0; ref_count = 0;

      repeat (3) @(posedge clk);
      rst_n = 1;
      @(posedge clk);
    end
  endtask

  task drive_push;
    input [WIDTH-1:0] v;
    begin
      @(negedge clk);
      push = 1; din = v; pop = 0;
      @(negedge clk);
      push = 0;
    end
  endtask

  task drive_pop;
    begin
      @(negedge clk);
      pop = 1; push = 0;
      @(negedge clk);
      pop = 0;
    end
  endtask

  task drive_push_pop;
    input [WIDTH-1:0] v;
    begin
      @(negedge clk);
      push = 1; din = v;
      pop  = 1;
      @(negedge clk);
      push = 0; pop = 0;
    end
  endtask

  // Scoreboard/checker
  always @(posedge clk) begin
    if (!rst_n) begin
      // keep reference in a known state during reset
      ref_wr <= 0;
      ref_rd <= 0;
      ref_count <= 0;
    end else begin
      // IMPORTANT: decide acceptance using DUT flags at posedge (no negedge sampling)
      wr_ok = (push && !full);
      rd_ok = (pop  && !empty);

      // If pop accepted, compare expected data
      if (rd_ok) begin
        exp = ref_mem[ref_rd];
        #1;
        if (dout !== exp) begin
          $fatal(1, "DATA MISMATCH: got=%0h exp=%0h", dout, exp);
        end

        // advance rd
        if (ref_rd == DEPTH-1) ref_rd = 0;
        else ref_rd = ref_rd + 1;

        ref_count = ref_count - 1;
      end

      // If push accepted, update ref model
      if (wr_ok) begin
        ref_mem[ref_wr] = din;

        // advance wr
        if (ref_wr == DEPTH-1) ref_wr = 0;
        else ref_wr = ref_wr + 1;

        ref_count = ref_count + 1;
      end

      // Give DUT combinational flags a tiny moment to update after NBA pointer updates
      #1;

      if (empty !== (ref_count == 0)) begin
        $fatal(1, "EMPTY mismatch: dut=%0b ref=%0b ref_count=%0d",
               empty, (ref_count==0), ref_count);
      end

      if (full !== (ref_count == DEPTH)) begin
        $fatal(1, "FULL mismatch: dut=%0b ref=%0b ref_count=%0d",
               full, (ref_count==DEPTH), ref_count);
      end
    end
  end

  initial begin
    $display("TB start");
    do_reset();

    // Fill to full
    for (i = 0; i < DEPTH; i = i + 1) begin
      drive_push(i[WIDTH-1:0]);
    end
    if (!full) $fatal(1, "Expected full after filling");

    // Overflow attempt (ignored)
    drive_push(8'hAA);
    if (!full) $fatal(1, "Expected still full after overflow attempt");

    // Drain to empty
    for (i = 0; i < DEPTH; i = i + 1) begin
      drive_pop();
    end
    if (!empty) $fatal(1, "Expected empty after draining");

    // Underflow attempt (ignored)
    drive_pop();
    if (!empty) $fatal(1, "Expected still empty after underflow attempt");

    // Wraparound stress
    for (i = 0; i < DEPTH*2; i = i + 1) begin
      drive_push(i[WIDTH-1:0]);
      if (i % 2 == 0) drive_pop();
    end
    while (!empty) drive_pop();

    // Simultaneous push+pop
    drive_push(8'h11);
    drive_push(8'h22);
    drive_push(8'h33);
    for (i = 0; i < 5; i = i + 1) begin
      drive_push_pop($random);
    end
    while (!empty) drive_pop();

    $display("ALL TESTS PASSED ✅");
    $finish;
  end

endmodule

wave.vcd
$date
	Fri Dec 19 18:05:34 2025
$end
$version
	Icarus Verilog
$end
$timescale
	1s
$end
$scope module tb_fifo $end
$var wire 1 ! full $end
$var wire 1 " empty $end
$var wire 8 # dout [7:0] $end
$var wire 32 $ count [31:0] $end
$var parameter 32 % DEPTH $end
$var parameter 32 & WIDTH $end
$var reg 1 ' clk $end
$var reg 8 ( din [7:0] $end
$var reg 8 ) exp [7:0] $end
$var reg 1 * pop $end
$var reg 1 + push $end
$var reg 1 , rst_n $end
$var integer 32 - i [31:0] $end
$var integer 32 . rd_ok [31:0] $end
$var integer 32 / ref_count [31:0] $end
$var integer 32 0 ref_rd [31:0] $end
$var integer 32 1 ref_wr [31:0] $end
$var integer 32 2 wr_ok [31:0] $end
$scope module dut $end
$var wire 1 ' clk $end
$var wire 8 3 din [7:0] $end
$var wire 1 ! full $end
$var wire 1 * pop $end
$var wire 1 + push $end
$var wire 1 4 rd_en $end
$var wire 1 , rst_n $end
$var wire 1 5 wr_en $end
$var wire 1 " empty $end
$var parameter 32 6 ADDR_W $end
$var parameter 32 7 DEPTH $end
$var parameter 32 8 WIDTH $end
$var reg 32 9 count [31:0] $end
$var reg 8 : dout [7:0] $end
$var reg 5 ; rd_ptr [4:0] $end
$var reg 5 < wr_ptr [4:0] $end
$scope function clog2 $end
$var integer 32 = i [31:0] $end
$var integer 32 > value [31:0] $end
$upscope $end
$upscope $end
$scope task do_reset $end
$upscope $end
$scope task drive_pop $end
$upscope $end
$scope task drive_push $end
$var reg 8 ? v [7:0] $end
$upscope $end
$scope task drive_push_pop $end
$var reg 8 @ v [7:0] $end
$upscope $end
$upscope $end
$enddefinitions $end
$comment Show the parameter values. $end
$dumpall
b1000 8
b10000 7
b100 6
b1000 &
b10000 %
$end
#0
$dumpvars
bx @
bx ?
bx >
bx =
bx <
bx ;
bx :
bx 9
05
04
b0 3
bx 2
b0 1
b0 0
b0 /
bx .
bx -
0,
0+
0*
bx )
b0 (
0'
bx $
bx #
x"
x!
$end
#5
0!
b0 #
b0 :
b0 $
b0 9
1"
b0 ;
b0 <
1'
#10
0'
#15
1'
#20
0'
#25
b0 .
b0 2
1,
1'
#30
0'
#35
b0 ?
b0 -
1'
#40
15
1+
0'
#45
0"
b1 <
b1 $
b1 9
b1 /
b1 1
b1 2
1'
#50
05
b1 ?
b1 -
0+
0'
#55
b0 2
1'
#60
15
b1 (
b1 3
1+
0'
#65
b10 <
b10 $
b10 9
b10 /
b10 1
b1 2
1'
#70
05
b10 ?
b10 -
0+
0'
#75
b0 2
1'
#80
15
b10 (
b10 3
1+
0'
#85
b11 <
b11 $
b11 9
b11 /
b11 1
b1 2
1'
#90
05
b11 ?
b11 -
0+
0'
#95
b0 2
1'
#100
15
b11 (
b11 3
1+
0'
#105
b100 <
b100 $
b100 9
b100 /
b100 1
b1 2
1'
#110
05
b100 ?
b100 -
0+
0'
#115
b0 2
1'
#120
15
b100 (
b100 3
1+
0'
#125
b101 <
b101 $
b101 9
b101 /
b101 1
b1 2
1'
#130
05
b101 ?
b101 -
0+
0'
#135
b0 2
1'
#140
15
b101 (
b101 3
1+
0'
#145
b110 <
b110 $
b110 9
b110 /
b110 1
b1 2
1'
#150
05
b110 ?
b110 -
0+
0'
#155
b0 2
1'
#160
15
b110 (
b110 3
1+
0'
#165
b111 <
b111 $
b111 9
b111 /
b111 1
b1 2
1'
#170
05
b111 ?
b111 -
0+
0'
#175
b0 2
1'
#180
15
b111 (
b111 3
1+
0'
#185
b1000 <
b1000 $
b1000 9
b1000 /
b1000 1
b1 2
1'
#190
05
b1000 ?
b1000 -
0+
0'
#195
b0 2
1'
#200
15
b1000 (
b1000 3
1+
0'
#205
b1001 <
b1001 $
b1001 9
b1001 /
b1001 1
b1 2
1'
#210
05
b1001 ?
b1001 -
0+
0'
#215
b0 2
1'
#220
15
b1001 (
b1001 3
1+
0'
#225
b1010 <
b1010 $
b1010 9
b1010 /
b1010 1
b1 2
1'
#230
05
b1010 ?
b1010 -
0+
0'
#235
b0 2
1'
#240
15
b1010 (
b1010 3
1+
0'
#245
b1011 <
b1011 $
b1011 9
b1011 /
b1011 1
b1 2
1'
#250
05
b1011 ?
b1011 -
0+
0'
#255
b0 2
1'
#260
15
b1011 (
b1011 3
1+
0'
#265
b1100 <
b1100 $
b1100 9
b1100 /
b1100 1
b1 2
1'
#270
05
b1100 ?
b1100 -
0+
0'
#275
b0 2
1'
#280
15
b1100 (
b1100 3
1+
0'
#285
b1101 <
b1101 $
b1101 9
b1101 /
b1101 1
b1 2
1'
#290
05
b1101 ?
b1101 -
0+
0'
#295
b0 2
1'
#300
15
b1101 (
b1101 3
1+
0'
#305
b1110 <
b1110 $
b1110 9
b1110 /
b1110 1
b1 2
1'
#310
05
b1110 ?
b1110 -
0+
0'
#315
b0 2
1'
#320
15
b1110 (
b1110 3
1+
0'
#325
b1111 <
b1111 $
b1111 9
b1111 /
b1111 1
b1 2
1'
#330
05
b1111 ?
b1111 -
0+
0'
#335
b0 2
1'
#340
15
b1111 (
b1111 3
1+
0'
#345
05
1!
b10000 <
b10000 $
b10000 9
b10000 /
b0 1
b1 2
1'
#350
b10101010 ?
b10000 -
0+
0'
#355
b0 2
1'
#360
b10101010 (
b10101010 3
1+
0'
#365
1'
#370
b0 -
0+
0'
#375
1'
#380
14
1*
0'
#385
0!
b1 ;
b1111 $
b1111 9
b0 )
b1 .
1'
#386
b1111 /
b1 0
#390
04
b1 -
0*
0'
#395
b0 .
1'
#400
14
1*
0'
#405
b1 #
b1 :
b10 ;
b1110 $
b1110 9
b1 )
b1 .
1'
#406
b1110 /
b10 0
#410
04
b10 -
0*
0'
#415
b0 .
1'
#420
14
1*
0'
#425
b10 #
b10 :
b11 ;
b1101 $
b1101 9
b10 )
b1 .
1'
#426
b1101 /
b11 0
#430
04
b11 -
0*
0'
#435
b0 .
1'
#440
14
1*
0'
#445
b11 #
b11 :
b100 ;
b1100 $
b1100 9
b11 )
b1 .
1'
#446
b1100 /
b100 0
#450
04
b100 -
0*
0'
#455
b0 .
1'
#460
14
1*
0'
#465
b100 #
b100 :
b101 ;
b1011 $
b1011 9
b100 )
b1 .
1'
#466
b1011 /
b101 0
#470
04
b101 -
0*
0'
#475
b0 .
1'
#480
14
1*
0'
#485
b101 #
b101 :
b110 ;
b1010 $
b1010 9
b101 )
b1 .
1'
#486
b1010 /
b110 0
#490
04
b110 -
0*
0'
#495
b0 .
1'
#500
14
1*
0'
#505
b110 #
b110 :
b111 ;
b1001 $
b1001 9
b110 )
b1 .
1'
#506
b1001 /
b111 0
#510
04
b111 -
0*
0'
#515
b0 .
1'
#520
14
1*
0'
#525
b111 #
b111 :
b1000 ;
b1000 $
b1000 9
b111 )
b1 .
1'
#526
b1000 /
b1000 0
#530
04
b1000 -
0*
0'
#535
b0 .
1'
#540
14
1*
0'
#545
b1000 #
b1000 :
b1001 ;
b111 $
b111 9
b1000 )
b1 .
1'
#546
b111 /
b1001 0
#550
04
b1001 -
0*
0'
#555
b0 .
1'
#560
14
1*
0'
#565
b1001 #
b1001 :
b1010 ;
b110 $
b110 9
b1001 )
b1 .
1'
#566
b110 /
b1010 0
#570
04
b1010 -
0*
0'
#575
b0 .
1'
#580
14
1*
0'
#585
b1010 #
b1010 :
b1011 ;
b101 $
b101 9
b1010 )
b1 .
1'
#586
b101 /
b1011 0
#590
04
b1011 -
0*
0'
#595
b0 .
1'
#600
14
1*
0'
#605
b1011 #
b1011 :
b1100 ;
b100 $
b100 9
b1011 )
b1 .
1'
#606
b100 /
b1100 0
#610
04
b1100 -
0*
0'
#615
b0 .
1'
#620
14
1*
0'
#625
b1100 #
b1100 :
b1101 ;
b11 $
b11 9
b1100 )
b1 .
1'
#626
b11 /
b1101 0
#630
04
b1101 -
0*
0'
#635
b0 .
1'
#640
14
1*
0'
#645
b1101 #
b1101 :
b1110 ;
b10 $
b10 9
b1101 )
b1 .
1'
#646
b10 /
b1110 0
#650
04
b1110 -
0*
0'
#655
b0 .
1'
#660
14
1*
0'
#665
b1110 #
b1110 :
b1111 ;
b1 $
b1 9
b1110 )
b1 .
1'
#666
b1 /
b1111 0
#670
04
b1111 -
0*
0'
#675
b0 .
1'
#680
14
1*
0'
#685
0!
04
b1111 #
b1111 :
1"
b10000 ;
b0 $
b0 9
b1111 )
b1 .
1'
#686
b0 /
b0 0
#690
b10000 -
0*
0'
#695
b0 .
1'
#700
1*
0'
#705
1'
#710
b0 ?
b0 -
0*
0'
#715
1'
#720
15
b0 (
b0 3
1+
0'
#725
0"
b10001 <
b1 $
b1 9
b1 /
b1 1
b1 2
1'
#730
05
0+
0'
#735
b0 2
1'
#740
14
1*
0'
#745
04
b0 #
b0 :
1"
b10001 ;
b0 $
b0 9
b0 )
b1 .
1'
#746
b0 /
b1 0
#750
b1 ?
b1 -
0*
0'
#755
b0 .
1'
#760
15
b1 (
b1 3
1+
0'
#765
0"
b10010 <
b1 $
b1 9
b1 /
b10 1
b1 2
1'
#770
05
b10 ?
b10 -
0+
0'
#775
b0 2
1'
#780
15
b10 (
b10 3
1+
0'
#785
b10011 <
b10 $
b10 9
b10 /
b11 1
b1 2
1'
#790
05
0+
0'
#795
b0 2
1'
#800
14
1*
0'
#805
b1 #
b1 :
b10010 ;
b1 $
b1 9
b1 )
b1 .
1'
#806
b1 /
b10 0
#810
04
b11 ?
b11 -
0*
0'
#815
b0 .
1'
#820
15
b11 (
b11 3
1+
0'
#825
b10100 <
b10 $
b10 9
b10 /
b100 1
b1 2
1'
#830
05
b100 ?
b100 -
0+
0'
#835
b0 2
1'
#840
15
b100 (
b100 3
1+
0'
#845
b10101 <
b11 $
b11 9
b11 /
b101 1
b1 2
1'
#850
05
0+
0'
#855
b0 2
1'
#860
14
1*
0'
#865
b10 #
b10 :
b10011 ;
b10 $
b10 9
b10 )
b1 .
1'
#866
b10 /
b11 0
#870
04
b101 ?
b101 -
0*
0'
#875
b0 .
1'
#880
15
b101 (
b101 3
1+
0'
#885
b10110 <
b11 $
b11 9
b11 /
b110 1
b1 2
1'
#890
05
b110 ?
b110 -
0+
0'
#895
b0 2
1'
#900
15
b110 (
b110 3
1+
0'
#905
b10111 <
b100 $
b100 9
b100 /
b111 1
b1 2
1'
#910
05
0+
0'
#915
b0 2
1'
#920
14
1*
0'
#925
b11 #
b11 :
b10100 ;
b11 $
b11 9
b11 )
b1 .
1'
#926
b11 /
b100 0
#930
04
b111 ?
b111 -
0*
0'
#935
b0 .
1'
#940
15
b111 (
b111 3
1+
0'
#945
b11000 <
b100 $
b100 9
b100 /
b1000 1
b1 2
1'
#950
05
b1000 ?
b1000 -
0+
0'
#955
b0 2
1'
#960
15
b1000 (
b1000 3
1+
0'
#965
b11001 <
b101 $
b101 9
b101 /
b1001 1
b1 2
1'
#970
05
0+
0'
#975
b0 2
1'
#980
14
1*
0'
#985
b100 #
b100 :
b10101 ;
b100 $
b100 9
b100 )
b1 .
1'
#986
b100 /
b101 0
#990
04
b1001 ?
b1001 -
0*
0'
#995
b0 .
1'
#1000
15
b1001 (
b1001 3
1+
0'
#1005
b11010 <
b101 $
b101 9
b101 /
b1010 1
b1 2
1'
#1010
05
b1010 ?
b1010 -
0+
0'
#1015
b0 2
1'
#1020
15
b1010 (
b1010 3
1+
0'
#1025
b11011 <
b110 $
b110 9
b110 /
b1011 1
b1 2
1'
#1030
05
0+
0'
#1035
b0 2
1'
#1040
14
1*
0'
#1045
b101 #
b101 :
b10110 ;
b101 $
b101 9
b101 )
b1 .
1'
#1046
b101 /
b110 0
#1050
04
b1011 ?
b1011 -
0*
0'
#1055
b0 .
1'
#1060
15
b1011 (
b1011 3
1+
0'
#1065
b11100 <
b110 $
b110 9
b110 /
b1100 1
b1 2
1'
#1070
05
b1100 ?
b1100 -
0+
0'
#1075
b0 2
1'
#1080
15
b1100 (
b1100 3
1+
0'
#1085
b11101 <
b111 $
b111 9
b111 /
b1101 1
b1 2
1'
#1090
05
0+
0'
#1095
b0 2
1'
#1100
14
1*
0'
#1105
b110 #
b110 :
b10111 ;
b110 $
b110 9
b110 )
b1 .
1'
#1106
b110 /
b111 0
#1110
04
b1101 ?
b1101 -
0*
0'
#1115
b0 .
1'
#1120
15
b1101 (
b1101 3
1+
0'
#1125
b11110 <
b111 $
b111 9
b111 /
b1110 1
b1 2
1'
#1130
05
b1110 ?
b1110 -
0+
0'
#1135
b0 2
1'
#1140
15
b1110 (
b1110 3
1+
0'
#1145
b11111 <
b1000 $
b1000 9
b1000 /
b1111 1
b1 2
1'
#1150
05
0+
0'
#1155
b0 2
1'
#1160
14
1*
0'
#1165
b111 #
b111 :
b11000 ;
b111 $
b111 9
b111 )
b1 .
1'
#1166
b111 /
b1000 0
#1170
04
b1111 ?
b1111 -
0*
0'
#1175
b0 .
1'
#1180
15
b1111 (
b1111 3
1+
0'
#1185
b0 <
b1000 $
b1000 9
b1000 /
b0 1
b1 2
1'
#1190
05
b10000 ?
b10000 -
0+
0'
#1195
b0 2
1'
#1200
15
b10000 (
b10000 3
1+
0'
#1205
b1 <
b1001 $
b1001 9
b1001 /
b1 1
b1 2
1'
#1210
05
0+
0'
#1215
b0 2
1'
#1220
14
1*
0'
#1225
b1000 #
b1000 :
b11001 ;
b1000 $
b1000 9
b1000 )
b1 .
1'
#1226
b1000 /
b1001 0
#1230
04
b10001 ?
b10001 -
0*
0'
#1235
b0 .
1'
#1240
15
b10001 (
b10001 3
1+
0'
#1245
b10 <
b1001 $
b1001 9
b1001 /
b10 1
b1 2
1'
#1250
05
b10010 ?
b10010 -
0+
0'
#1255
b0 2
1'
#1260
15
b10010 (
b10010 3
1+
0'
#1265
b11 <
b1010 $
b1010 9
b1010 /
b11 1
b1 2
1'
#1270
05
0+
0'
#1275
b0 2
1'
#1280
14
1*
0'
#1285
b1001 #
b1001 :
b11010 ;
b1001 $
b1001 9
b1001 )
b1 .
1'
#1286
b1001 /
b1010 0
#1290
04
b10011 ?
b10011 -
0*
0'
#1295
b0 .
1'
#1300
15
b10011 (
b10011 3
1+
0'
#1305
b100 <
b1010 $
b1010 9
b1010 /
b100 1
b1 2
1'
#1310
05
b10100 ?
b10100 -
0+
0'
#1315
b0 2
1'
#1320
15
b10100 (
b10100 3
1+
0'
#1325
b101 <
b1011 $
b1011 9
b1011 /
b101 1
b1 2
1'
#1330
05
0+
0'
#1335
b0 2
1'
#1340
14
1*
0'
#1345
b1010 #
b1010 :
b11011 ;
b1010 $
b1010 9
b1010 )
b1 .
1'
#1346
b1010 /
b1011 0
#1350
04
b10101 ?
b10101 -
0*
0'
#1355
b0 .
1'
#1360
15
b10101 (
b10101 3
1+
0'
#1365
b110 <
b1011 $
b1011 9
b1011 /
b110 1
b1 2
1'
#1370
05
b10110 ?
b10110 -
0+
0'
#1375
b0 2
1'
#1380
15
b10110 (
b10110 3
1+
0'
#1385
b111 <
b1100 $
b1100 9
b1100 /
b111 1
b1 2
1'
#1390
05
0+
0'
#1395
b0 2
1'
#1400
14
1*
0'
#1405
b1011 #
b1011 :
b11100 ;
b1011 $
b1011 9
b1011 )
b1 .
1'
#1406
b1011 /
b1100 0
#1410
04
b10111 ?
b10111 -
0*
0'
#1415
b0 .
1'
#1420
15
b10111 (
b10111 3
1+
0'
#1425
b1000 <
b1100 $
b1100 9
b1100 /
b1000 1
b1 2
1'
#1430
05
b11000 ?
b11000 -
0+
0'
#1435
b0 2
1'
#1440
15
b11000 (
b11000 3
1+
0'
#1445
b1001 <
b1101 $
b1101 9
b1101 /
b1001 1
b1 2
1'
#1450
05
0+
0'
#1455
b0 2
1'
#1460
14
1*
0'
#1465
b1100 #
b1100 :
b11101 ;
b1100 $
b1100 9
b1100 )
b1 .
1'
#1466
b1100 /
b1101 0
#1470
04
b11001 ?
b11001 -
0*
0'
#1475
b0 .
1'
#1480
15
b11001 (
b11001 3
1+
0'
#1485
b1010 <
b1101 $
b1101 9
b1101 /
b1010 1
b1 2
1'
#1490
05
b11010 ?
b11010 -
0+
0'
#1495
b0 2
1'
#1500
15
b11010 (
b11010 3
1+
0'
#1505
b1011 <
b1110 $
b1110 9
b1110 /
b1011 1
b1 2
1'
#1510
05
0+
0'
#1515
b0 2
1'
#1520
14
1*
0'
#1525
b1101 #
b1101 :
b11110 ;
b1101 $
b1101 9
b1101 )
b1 .
1'
#1526
b1101 /
b1110 0
#1530
04
b11011 ?
b11011 -
0*
0'
#1535
b0 .
1'
#1540
15
b11011 (
b11011 3
1+
0'
#1545
b1100 <
b1110 $
b1110 9
b1110 /
b1100 1
b1 2
1'
#1550
05
b11100 ?
b11100 -
0+
0'
#1555
b0 2
1'
#1560
15
b11100 (
b11100 3
1+
0'
#1565
b1101 <
b1111 $
b1111 9
b1111 /
b1101 1
b1 2
1'
#1570
05
0+
0'
#1575
b0 2
1'
#1580
14
1*
0'
#1585
b1110 #
b1110 :
b11111 ;
b1110 $
b1110 9
b1110 )
b1 .
1'
#1586
b1110 /
b1111 0
#1590
04
b11101 ?
b11101 -
0*
0'
#1595
b0 .
1'
#1600
15
b11101 (
b11101 3
1+
0'
#1605
b1110 <
b1111 $
b1111 9
b1111 /
b1110 1
b1 2
1'
#1610
05
b11110 ?
b11110 -
0+
0'
#1615
b0 2
1'
#1620
15
b11110 (
b11110 3
1+
0'
#1625
05
1!
b1111 <
b10000 $
b10000 9
b10000 /
b1111 1
b1 2
1'
#1630
0+
0'
#1635
b0 2
1'
#1640
14
1*
0'
#1645
0!
b1111 #
b1111 :
b0 ;
b1111 $
b1111 9
b1111 )
b1 .
1'
#1646
b1111 /
b0 0
#1650
04
b11111 ?
b11111 -
0*
0'
#1655
b0 .
1'
#1660
15
b11111 (
b11111 3
1+
0'
#1665
05
1!
b10000 <
b10000 $
b10000 9
b10000 /
b0 1
b1 2
1'
#1670
b100000 -
0+
0'
#1675
b0 2
1'
#1680
14
1*
0'
#1685
0!
b10000 #
b10000 :
b1 ;
b1111 $
b1111 9
b10000 )
b1 .
1'
#1686
b1111 /
b1 0
#1690
04
0*
0'
#1695
b0 .
1'
#1700
14
1*
0'
#1705
b10001 #
b10001 :
b10 ;
b1110 $
b1110 9
b10001 )
b1 .
1'
#1706
b1110 /
b10 0
#1710
04
0*
0'
#1715
b0 .
1'
#1720
14
1*
0'
#1725
b10010 #
b10010 :
b11 ;
b1101 $
b1101 9
b10010 )
b1 .
1'
#1726
b1101 /
b11 0
#1730
04
0*
0'
#1735
b0 .
1'
#1740
14
1*
0'
#1745
b10011 #
b10011 :
b100 ;
b1100 $
b1100 9
b10011 )
b1 .
1'
#1746
b1100 /
b100 0
#1750
04
0*
0'
#1755
b0 .
1'
#1760
14
1*
0'
#1765
b10100 #
b10100 :
b101 ;
b1011 $
b1011 9
b10100 )
b1 .
1'
#1766
b1011 /
b101 0
#1770
04
0*
0'
#1775
b0 .
1'
#1780
14
1*
0'
#1785
b10101 #
b10101 :
b110 ;
b1010 $
b1010 9
b10101 )
b1 .
1'
#1786
b1010 /
b110 0
#1790
04
0*
0'
#1795
b0 .
1'
#1800
14
1*
0'
#1805
b10110 #
b10110 :
b111 ;
b1001 $
b1001 9
b10110 )
b1 .
1'
#1806
b1001 /
b111 0
#1810
04
0*
0'
#1815
b0 .
1'
#1820
14
1*
0'
#1825
b10111 #
b10111 :
b1000 ;
b1000 $
b1000 9
b10111 )
b1 .
1'
#1826
b1000 /
b1000 0
#1830
04
0*
0'
#1835
b0 .
1'
#1840
14
1*
0'
#1845
b11000 #
b11000 :
b1001 ;
b111 $
b111 9
b11000 )
b1 .
1'
#1846
b111 /
b1001 0
#1850
04
0*
0'
#1855
b0 .
1'
#1860
14
1*
0'
#1865
b11001 #
b11001 :
b1010 ;
b110 $
b110 9
b11001 )
b1 .
1'
#1866
b110 /
b1010 0
#1870
04
0*
0'
#1875
b0 .
1'
#1880
14
1*
0'
#1885
b11010 #
b11010 :
b1011 ;
b101 $
b101 9
b11010 )
b1 .
1'
#1886
b101 /
b1011 0
#1890
04
0*
0'
#1895
b0 .
1'
#1900
14
1*
0'
#1905
b11011 #
b11011 :
b1100 ;
b100 $
b100 9
b11011 )
b1 .
1'
#1906
b100 /
b1100 0
#1910
04
0*
0'
#1915
b0 .
1'
#1920
14
1*
0'
#1925
b11100 #
b11100 :
b1101 ;
b11 $
b11 9
b11100 )
b1 .
1'
#1926
b11 /
b1101 0
#1930
04
0*
0'
#1935
b0 .
1'
#1940
14
1*
0'
#1945
b11101 #
b11101 :
b1110 ;
b10 $
b10 9
b11101 )
b1 .
1'
#1946
b10 /
b1110 0
#1950
04
0*
0'
#1955
b0 .
1'
#1960
14
1*
0'
#1965
b11110 #
b11110 :
b1111 ;
b1 $
b1 9
b11110 )
b1 .
1'
#1966
b1 /
b1111 0
#1970
04
0*
0'
#1975
b0 .
1'
#1980
14
1*
0'
#1985
0!
04
b11111 #
b11111 :
1"
b10000 ;
b0 $
b0 9
b11111 )
b1 .
1'
#1986
b0 /
b0 0
#1990
b10001 ?
0*
0'
#1995
b0 .
1'
#2000
15
b10001 (
b10001 3
1+
0'
#2005
0"
b10001 <
b1 $
b1 9
b1 /
b1 1
b1 2
1'
#2010
05
b100010 ?
0+
0'
#2015
b0 2
1'
#2020
15
b100010 (
b100010 3
1+
0'
#2025
b10010 <
b10 $
b10 9
b10 /
b10 1
b1 2
1'
#2030
05
b110011 ?
0+
0'
#2035
b0 2
1'
#2040
15
b110011 (
b110011 3
1+
0'
#2045
b10011 <
b11 $
b11 9
b11 /
b11 1
b1 2
1'
#2050
05
b100100 @
b0 -
0+
0'
#2055
b0 2
1'
#2060
14
15
1*
b100100 (
b100100 3
1+
0'
#2065
b10001 #
b10001 :
b10001 ;
b10100 <
b10001 )
b1 .
b1 2
1'
#2066
b100 1
b11 /
b1 0
#2070
04
05
b10000001 @
b1 -
0*
0+
0'
#2075
b0 .
b0 2
1'
#2080
14
15
1*
b10000001 (
b10000001 3
1+
0'
#2085
b100010 #
b100010 :
b10010 ;
b10101 <
b100010 )
b1 .
b1 2
1'
#2086
b101 1
b11 /
b10 0
#2090
04
05
b1001 @
b10 -
0*
0+
0'
#2095
b0 .
b0 2
1'
#2100
14
15
1*
b1001 (
b1001 3
1+
0'
#2105
b110011 #
b110011 :
b10011 ;
b10110 <
b110011 )
b1 .
b1 2
1'
#2106
b110 1
b11 /
b11 0
#2110
04
05
b1100011 @
b11 -
0*
0+
0'
#2115
b0 .
b0 2
1'
#2120
14
15
1*
b1100011 (
b1100011 3
1+
0'
#2125
b100100 #
b100100 :
b10100 ;
b10111 <
b100100 )
b1 .
b1 2
1'
#2126
b111 1
b11 /
b100 0
#2130
04
05
b1101 @
b100 -
0*
0+
0'
#2135
b0 .
b0 2
1'
#2140
14
15
1*
b1101 (
b1101 3
1+
0'
#2145
b10000001 #
b10000001 :
b10101 ;
b11000 <
b10000001 )
b1 .
b1 2
1'
#2146
b1000 1
b11 /
b101 0
#2150
04
05
b101 -
0*
0+
0'
#2155
b0 .
b0 2
1'
#2160
14
1*
0'
#2165
b1001 #
b1001 :
b10110 ;
b10 $
b10 9
b1001 )
b1 .
1'
#2166
b10 /
b110 0
#2170
04
0*
0'
#2175
b0 .
1'
#2180
14
1*
0'
#2185
b1100011 #
b1100011 :
b10111 ;
b1 $
b1 9
b1100011 )
b1 .
1'
#2186
b1 /
b111 0
#2190
04
0*
0'
#2195
b0 .
1'
#2200
14
1*
0'
#2205
04
b1101 #
b1101 :
1"
b11000 ;
b0 $
b0 9
b1101 )
b1 .
1'
#2206
b0 /
b1000 0
#2210
0*
0'
